promptwithoptions/__init__.py
promptwithoptions/promptwithoptions.py
promptwithoptions-1.0.3.dist-info/LICENSE
promptwithoptions-1.0.3.dist-info/WHEEL
promptwithoptions-1.0.3.dist-info/METADATA
promptwithoptions-1.0.3.dist-info/RECORD
