Metadata-Version: 2.1
Name: promptwithoptions
Version: 1.0.3
Summary: Input for command line questions with options
Home-page: https://github.com/silkyanteater/promptwithoptions
License: MIT
Keywords: command line,input,options
Author: silkyanteater
Author-email: cyclopesrufus@gmail.com
Requires-Python: >=3.6,<4.0
Classifier: License :: OSI Approved :: MIT License
Classifier: Programming Language :: Python :: 3
Classifier: Programming Language :: Python :: 3.6
Classifier: Programming Language :: Python :: 3.7
Classifier: Programming Language :: Python :: 3.8
Classifier: Programming Language :: Python :: 3.9
Project-URL: Repository, https://github.com/silkyanteater/promptwithoptions
